{
  "attributes": [
    {
      "default": "nil",
      "size": null,
      "type": "uuid",
      "source": "id",
      "references": null,
      "allow_nil?": false,
      "primary_key?": true,
      "generated?": false
    },
    {
      "default": "nil",
      "size": null,
      "type": "utc_datetime_usec",
      "source": "created_at",
      "references": null,
      "allow_nil?": false,
      "primary_key?": false,
      "generated?": false
    },
    {
      "default": "nil",
      "size": null,
      "type": "utc_datetime_usec",
      "source": "updated_at",
      "references": null,
      "allow_nil?": false,
      "primary_key?": false,
      "generated?": false
    },
    {
      "default": "nil",
      "size": null,
      "type": "text",
      "source": "username",
      "references": null,
      "allow_nil?": false,
      "primary_key?": false,
      "generated?": false
    },
    {
      "default": "nil",
      "size": null,
      "type": "bigint",
      "source": "xhain_account_id",
      "references": null,
      "allow_nil?": false,
      "primary_key?": false,
      "generated?": false
    },
    {
      "default": "nil",
      "size": null,
      "type": "text",
      "source": "tree_name",
      "references": null,
      "allow_nil?": false,
      "primary_key?": false,
      "generated?": false
    },
    {
      "default": "nil",
      "size": null,
      "type": "text",
      "source": "ssh_public_key",
      "references": null,
      "allow_nil?": true,
      "primary_key?": false,
      "generated?": false
    },
    {
      "default": "nil",
      "size": null,
      "type": "boolean",
      "source": "is_manual_entry",
      "references": null,
      "allow_nil?": false,
      "primary_key?": false,
      "generated?": false
    },
    {
      "default": "nil",
      "size": null,
      "type": "boolean",
      "source": "is_active",
      "references": null,
      "allow_nil?": false,
      "primary_key?": false,
      "generated?": false
    },
    {
      "default": "nil",
      "size": null,
      "type": "text",
      "source": "matrix_contact",
      "references": null,
      "allow_nil?": true,
      "primary_key?": false,
      "generated?": false
    },
    {
      "default": "nil",
      "size": null,
      "type": "text",
      "source": "email",
      "references": null,
      "allow_nil?": true,
      "primary_key?": false,
      "generated?": false
    },
    {
      "default": "nil",
      "size": null,
      "type": "utc_datetime_usec",
      "source": "archived_at",
      "references": null,
      "allow_nil?": true,
      "primary_key?": false,
      "generated?": false
    }
  ],
  "table": "members",
  "hash": "6D8EFC33DC4A944007D61D6A4DD1AAE4212095834E90DA73B78320D2A1DA6C6B",
  "multitenancy": {
    "global": null,
    "attribute": null,
    "strategy": null
  },
  "identities": [
    {
      "name": "unique_username",
      "keys": [
        "username"
      ],
      "base_filter": null,
      "nils_distinct?": true,
      "index_name": "members_unique_username_index"
    }
  ],
  "repo": "Elixir.Valkyrie.Repo",
  "strict?": false,
  "custom_indexes": [],
  "base_filter": null,
  "custom_statements": [],
  "has_create_action": true
}